LICENSE
MANIFEST.in
README.md
setup.py
django_template/manage.py
django_template.egg-info/PKG-INFO
django_template.egg-info/SOURCES.txt
django_template.egg-info/dependency_links.txt
django_template.egg-info/entry_points.txt
django_template.egg-info/requires.txt
django_template.egg-info/top_level.txt
django_template/apps/__init__.py
django_template/apps/app/__init__.py
django_template/apps/app/admin.py
django_template/apps/app/apps.py
django_template/apps/app/models.py
django_template/apps/app/views.py
django_template/apps/app/migrations/__init__.py
django_template/apps/app/tests/integration/steps/test_admin.py
django_template/apps/app/tests/integration/steps/test_views.py
django_template/apps/app/tests/unit/unit_test.py
django_template/project/__init__.py
django_template/project/urls.py
django_template/project/wsgi.py
django_template/project/settings/development.py
django_template/project/settings/production.py
django_template/project/settings/testing.py